{"directed": false, "multigraph": false, "graph": [], "nodes": [{"boundary_node": true, "boundary_perim": 0.2894598487049155, "area": 0.017203923388500166, "STATEFP10": "34", "COUNTYFP10": "017", "COUNTYNS10": "00882278", "GEOID10": "34017", "NAME10": "Hudson", "NAMELSAD10": "Hudson County", "LSAD10": "06", "CLASSFP10": "H1", "MTFCC10": "G4020", "CSAFP10": "408", "CBSAFP10": "35620", "METDIVFP10": "35644", "FUNCSTAT10": "A", "ALAND10": 119634159, "AWATER10": 41755598, "INTPTLAT10": "+40.7313836", "INTPTLON10": "-074.0786266", "POP10": 634266, "UPOP": 634266, "RPOP": 0.0, "C_X": -74.07593588479614, "C_Y": 40.73094402147296, "TOTPOP": 634266, "UTOTPOP": 634266, "RTOTPOP": 0.0, "NH_WHITE": 195510, "UNH_WHITE": 195510, "RNH_WHITE": 0.0, "NH_BLACK": 71315, "UNH_BLACK": 71315, "RNH_BLACK": 0.0, "NH_AMIN": 935, "UNH_AMIN": 935, "RNH_AMIN": 0.0, "NH_ASIAN": 83825, "UNH_ASIAN": 83825, "RNH_ASIAN": 0.0, "NH_NHPI": 176, "UNH_NHPI": 176, "RNH_NHPI": 0.0, "NH_OTHER": 4251, "UNH_OTHER": 4251, "RNH_OTHER": 0.0, "NH_2MORE": 10401, "UNH_2MORE": 10401, "RNH_2MORE": 0.0, "HISP": 267853, "UHISP": 267853, "RHISP": 0.0, "H_WHITE": 147282, "UH_WHITE": 147282, "RH_WHITE": 0.0, "H_BLACK": 12610, "UH_BLACK": 12610, "RH_BLACK": 0.0, "H_AMIN": 3146, "UH_AMIN": 3146, "RH_AMIN": 0.0, "H_ASIAN": 1099, "UH_ASIAN": 1099, "RH_ASIAN": 0.0, "H_NHPI": 168, "UH_NHPI": 168, "RH_NHPI": 0.0, "H_OTHER": 86122, "UH_OTHER": 86122, "RH_OTHER": 0.0, "H_2MORE": 17426, "UH_2MORE": 17426, "RH_2MORE": 0.0, "VAP": 503104, "UVAP": 503104, "RVAP": 0.0, "HVAP": 200642, "UHVAP": 200642, "RHVAP": 0.0, "WVAP": 168189, "UWVAP": 168189, "RWVAP": 0.0, "BVAP": 53637, "UBVAP": 53637, "RBVAP": 0.0, "AMINVAP": 606, "UAMINVAP": 606, "RAMINVAP": 0.0, "ASIANVAP": 69894, "UASIANVAP": 69894, "RASIANVAP": 0.0, "NHPIVAP": 136, "UNHPIVAP": 136, "RNHPIVAP": 0.0, "OTHERVAP": 3050, "UOTHERVAP": 3050, "ROTHERVAP": 0.0, "2MOREVAP": 6950, "U2MOREVAP": 6950, "R2MOREVAP": 0.0, "id": 0}, {"boundary_node": true, "boundary_perim": 0.30904206403039636, "area": 0.18212836665649942, "STATEFP10": "34", "COUNTYFP10": "001", "COUNTYNS10": "00882270", "GEOID10": "34001", "NAME10": "Atlantic", "NAMELSAD10": "Atlantic County", "LSAD10": "06", "CLASSFP10": "H1", "MTFCC10": "G4020", "CSAFP10": "0", "CBSAFP10": "12100", "METDIVFP10": "0", "FUNCSTAT10": "A", "ALAND10": 1439267859, "AWATER10": 300755451, "INTPTLAT10": "+39.4693540", "INTPTLON10": "-074.6337583", "POP10": 274549, "UPOP": 239644, "RPOP": 34905.0, "C_X": -74.63373320212972, "C_Y": 39.46883381383935, "TOTPOP": 274549, "UTOTPOP": 239644, "RTOTPOP": 34905.0, "NH_WHITE": 160871, "UNH_WHITE": 132736, "RNH_WHITE": 28135.0, "NH_BLACK": 40882, "UNH_BLACK": 38333, "RNH_BLACK": 2549.0, "NH_AMIN": 488, "UNH_AMIN": 418, "RNH_AMIN": 70.0, "NH_ASIAN": 20419, "UNH_ASIAN": 19834, "RNH_ASIAN": 585.0, "NH_NHPI": 60, "UNH_NHPI": 53, "RNH_NHPI": 7.0, "NH_OTHER": 463, "UNH_OTHER": 445, "RNH_OTHER": 18.0, "NH_2MORE": 5125, "UNH_2MORE": 4578, "RNH_2MORE": 547.0, "HISP": 46241, "UHISP": 43247, "RHISP": 2994.0, "H_WHITE": 18695, "UH_WHITE": 17214, "RH_WHITE": 1481.0, "H_BLACK": 3256, "UH_BLACK": 3117, "RH_BLACK": 139.0, "H_AMIN": 562, "UH_AMIN": 531, "RH_AMIN": 31.0, "H_ASIAN": 176, "UH_ASIAN": 164, "RH_ASIAN": 12.0, "H_NHPI": 32, "UH_NHPI": 32, "RH_NHPI": 0.0, "H_OTHER": 19755, "UH_OTHER": 18683, "RH_OTHER": 1072.0, "H_2MORE": 3765, "UH_2MORE": 3506, "RH_2MORE": 259.0, "VAP": 210661, "UVAP": 183791, "RVAP": 26870.0, "HVAP": 30442, "UHVAP": 28474, "RHVAP": 1968.0, "WVAP": 131471, "UWVAP": 109273, "RWVAP": 22198.0, "BVAP": 29928, "UBVAP": 27996, "RBVAP": 1932.0, "AMINVAP": 360, "UAMINVAP": 301, "RAMINVAP": 59.0, "ASIANVAP": 15407, "UASIANVAP": 14968, "RASIANVAP": 439.0, "NHPIVAP": 47, "UNHPIVAP": 41, "RNHPIVAP": 6.0, "OTHERVAP": 268, "UOTHERVAP": 259, "ROTHERVAP": 9.0, "2MOREVAP": 2738, "U2MOREVAP": 2479, "R2MOREVAP": 259.0, "id": 1}, {"boundary_node": true, "boundary_perim": 0.5702574887895205, "area": 0.06833516027449978, "STATEFP10": "34", "COUNTYFP10": "003", "COUNTYNS10": "00882271", "GEOID10": "34003", "NAME10": "Bergen", "NAMELSAD10": "Bergen County", "LSAD10": "06", "CLASSFP10": "H1", "MTFCC10": "G4020", "CSAFP10": "408", "CBSAFP10": "35620", "METDIVFP10": "35644", "FUNCSTAT10": "A", "ALAND10": 603490137, "AWATER10": 35385294, "INTPTLAT10": "+40.9590904", "INTPTLON10": "-074.0745218", "POP10": 905116, "UPOP": 904197, "RPOP": 919.0, "C_X": -74.07440908531777, "C_Y": 40.959773057536566, "TOTPOP": 905116, "UTOTPOP": 904197, "RTOTPOP": 919.0, "NH_WHITE": 566053, "UNH_WHITE": 565345, "RNH_WHITE": 708.0, "NH_BLACK": 46850, "UNH_BLACK": 46819, "RNH_BLACK": 31.0, "NH_AMIN": 869, "UNH_AMIN": 817, "RNH_AMIN": 52.0, "NH_ASIAN": 130491, "UNH_ASIAN": 130462, "RNH_ASIAN": 29.0, "NH_NHPI": 173, "UNH_NHPI": 173, "RNH_NHPI": 0.0, "NH_OTHER": 2568, "UNH_OTHER": 2568, "RNH_OTHER": 0.0, "NH_2MORE": 12831, "UNH_2MORE": 12801, "RNH_2MORE": 30.0, "HISP": 145281, "UHISP": 145212, "RHISP": 69.0, "H_WHITE": 84650, "UH_WHITE": 84600, "RH_WHITE": 50.0, "H_BLACK": 5623, "UH_BLACK": 5623, "RH_BLACK": 0.0, "H_AMIN": 1192, "UH_AMIN": 1181, "RH_AMIN": 11.0, "H_ASIAN": 838, "UH_ASIAN": 838, "RH_ASIAN": 0.0, "H_NHPI": 56, "UH_NHPI": 56, "RH_NHPI": 0.0, "H_OTHER": 43043, "UH_OTHER": 43036, "RH_OTHER": 7.0, "H_2MORE": 9879, "UH_2MORE": 9878, "RH_2MORE": 1.0, "VAP": 700711, "UVAP": 700049, "RVAP": 662.0, "HVAP": 104506, "UHVAP": 104462, "RHVAP": 44.0, "WVAP": 450437, "UWVAP": 449920, "RWVAP": 517.0, "BVAP": 36048, "UBVAP": 36023, "RBVAP": 25.0, "AMINVAP": 590, "UAMINVAP": 546, "RAMINVAP": 44.0, "ASIANVAP": 100038, "UASIANVAP": 100020, "RASIANVAP": 18.0, "NHPIVAP": 145, "UNHPIVAP": 145, "RNHPIVAP": 0.0, "OTHERVAP": 1689, "UOTHERVAP": 1689, "ROTHERVAP": 0.0, "2MOREVAP": 7258, "U2MOREVAP": 7244, "R2MOREVAP": 14.0, "id": 2}, {"boundary_node": true, "boundary_perim": 0.8368456508630866, "area": 0.10036885556250026, "STATEFP10": "34", "COUNTYFP10": "041", "COUNTYNS10": "00882237", "GEOID10": "34041", "NAME10": "Warren", "NAMELSAD10": "Warren County", "LSAD10": "06", "CLASSFP10": "H1", "MTFCC10": "G4020", "CSAFP10": "0", "CBSAFP10": "10900", "METDIVFP10": "0", "FUNCSTAT10": "A", "ALAND10": 924412063, "AWATER10": 15383769, "INTPTLAT10": "+40.8535238", "INTPTLON10": "-075.0095420", "POP10": 108692, "UPOP": 67862, "RPOP": 40830.0, "C_X": -74.99701052677787, "C_Y": 40.85724909789597, "TOTPOP": 108692, "UTOTPOP": 67862, "RTOTPOP": 40830.0, "NH_WHITE": 93165, "UNH_WHITE": 55479, "RNH_WHITE": 37686.0, "NH_BLACK": 3592, "UNH_BLACK": 2960, "RNH_BLACK": 632.0, "NH_AMIN": 107, "UNH_AMIN": 66, "RNH_AMIN": 41.0, "NH_ASIAN": 2642, "UNH_ASIAN": 2109, "RNH_ASIAN": 533.0, "NH_NHPI": 19, "UNH_NHPI": 16, "RNH_NHPI": 3.0, "NH_OTHER": 140, "UNH_OTHER": 105, "RNH_OTHER": 35.0, "NH_2MORE": 1368, "UNH_2MORE": 1010, "RNH_2MORE": 358.0, "HISP": 7659, "UHISP": 6117, "RHISP": 1542.0, "H_WHITE": 4972, "UH_WHITE": 3813, "RH_WHITE": 1159.0, "H_BLACK": 226, "UH_BLACK": 194, "RH_BLACK": 32.0, "H_AMIN": 48, "UH_AMIN": 38, "RH_AMIN": 10.0, "H_ASIAN": 31, "UH_ASIAN": 26, "RH_ASIAN": 5.0, "H_NHPI": 11, "UH_NHPI": 11, "RH_NHPI": 0.0, "H_OTHER": 1824, "UH_OTHER": 1589, "RH_OTHER": 235.0, "H_2MORE": 547, "UH_2MORE": 446, "RH_2MORE": 101.0, "VAP": 83084, "UVAP": 51799, "RVAP": 31285.0, "HVAP": 4975, "UHVAP": 4004, "RHVAP": 971.0, "WVAP": 72927, "UWVAP": 43694, "RWVAP": 29233.0, "BVAP": 2486, "UBVAP": 2029, "RBVAP": 457.0, "AMINVAP": 82, "UAMINVAP": 47, "RAMINVAP": 35.0, "ASIANVAP": 1888, "UASIANVAP": 1491, "RASIANVAP": 397.0, "NHPIVAP": 18, "UNHPIVAP": 16, "RNHPIVAP": 2.0, "OTHERVAP": 80, "UOTHERVAP": 60, "ROTHERVAP": 20.0, "2MOREVAP": 628, "U2MOREVAP": 458, "R2MOREVAP": 170.0, "id": 3}, {"boundary_node": true, "boundary_perim": 0.35941581648232246, "area": 0.0917299334319996, "STATEFP10": "34", "COUNTYFP10": "015", "COUNTYNS10": "00882277", "GEOID10": "34015", "NAME10": "Gloucester", "NAMELSAD10": "Gloucester County", "LSAD10": "06", "CLASSFP10": "H1", "MTFCC10": "G4020", "CSAFP10": "428", "CBSAFP10": "37980", "METDIVFP10": "15804", "FUNCSTAT10": "A", "ALAND10": 833989655, "AWATER10": 39296178, "INTPTLAT10": "+39.7210193", "INTPTLON10": "-075.1437076", "POP10": 288288, "UPOP": 264228, "RPOP": 24060.0, "C_X": -75.14166953482628, "C_Y": 39.71731327088571, "TOTPOP": 288288, "UTOTPOP": 264228, "RTOTPOP": 24060.0, "NH_WHITE": 233695, "UNH_WHITE": 213270, "RNH_WHITE": 20425.0, "NH_BLACK": 27906, "UNH_BLACK": 25927, "RNH_BLACK": 1979.0, "NH_AMIN": 361, "UNH_AMIN": 328, "RNH_AMIN": 33.0, "NH_ASIAN": 7534, "UNH_ASIAN": 7241, "RNH_ASIAN": 293.0, "NH_NHPI": 62, "UNH_NHPI": 60, "RNH_NHPI": 2.0, "NH_OTHER": 310, "UNH_OTHER": 269, "RNH_OTHER": 41.0, "NH_2MORE": 4708, "UNH_2MORE": 4380, "RNH_2MORE": 328.0, "HISP": 13712, "UHISP": 12753, "RHISP": 959.0, "H_WHITE": 7195, "UH_WHITE": 6688, "RH_WHITE": 507.0, "H_BLACK": 1100, "UH_BLACK": 1036, "RH_BLACK": 64.0, "H_AMIN": 140, "UH_AMIN": 126, "RH_AMIN": 14.0, "H_ASIAN": 75, "UH_ASIAN": 72, "RH_ASIAN": 3.0, "H_NHPI": 33, "UH_NHPI": 33, "RH_NHPI": 0.0, "H_OTHER": 3745, "UH_OTHER": 3456, "RH_OTHER": 289.0, "H_2MORE": 1424, "UH_2MORE": 1342, "RH_2MORE": 82.0, "VAP": 218027, "UVAP": 199525, "RVAP": 18502.0, "HVAP": 8555, "UHVAP": 7927, "RHVAP": 628.0, "WVAP": 181249, "UWVAP": 165344, "RWVAP": 15905.0, "BVAP": 20114, "UBVAP": 18566, "RBVAP": 1548.0, "AMINVAP": 278, "UAMINVAP": 251, "RAMINVAP": 27.0, "ASIANVAP": 5488, "UASIANVAP": 5287, "RASIANVAP": 201.0, "NHPIVAP": 46, "UNHPIVAP": 44, "RNHPIVAP": 2.0, "OTHERVAP": 174, "UOTHERVAP": 155, "ROTHERVAP": 19.0, "2MOREVAP": 2123, "U2MOREVAP": 1951, "R2MOREVAP": 172.0, "id": 4}, {"boundary_node": true, "boundary_perim": 0.6209415498666915, "area": 0.10109026986000033, "STATEFP10": "34", "COUNTYFP10": "033", "COUNTYNS10": "00882233", "GEOID10": "34033", "NAME10": "Salem", "NAMELSAD10": "Salem County", "LSAD10": "06", "CLASSFP10": "H1", "MTFCC10": "G4020", "CSAFP10": "428", "CBSAFP10": "37980", "METDIVFP10": "48864", "FUNCSTAT10": "A", "ALAND10": 859613601, "AWATER10": 104713321, "INTPTLAT10": "+39.5738282", "INTPTLON10": "-075.3573559", "POP10": 66083, "UPOP": 36147, "RPOP": 29936.0, "C_X": -75.35791180720943, "C_Y": 39.57658475701467, "TOTPOP": 66083, "UTOTPOP": 36147, "RTOTPOP": 29936.0, "NH_WHITE": 50736, "UNH_WHITE": 24668, "RNH_WHITE": 26068.0, "NH_BLACK": 8940, "UNH_BLACK": 6968, "RNH_BLACK": 1972.0, "NH_AMIN": 187, "UNH_AMIN": 93, "RNH_AMIN": 94.0, "NH_ASIAN": 548, "UNH_ASIAN": 342, "RNH_ASIAN": 206.0, "NH_NHPI": 10, "UNH_NHPI": 4, "RNH_NHPI": 6.0, "NH_OTHER": 47, "UNH_OTHER": 26, "RNH_OTHER": 21.0, "NH_2MORE": 1108, "UNH_2MORE": 686, "RNH_2MORE": 422.0, "HISP": 4507, "UHISP": 3360, "RHISP": 1147.0, "H_WHITE": 2021, "UH_WHITE": 1405, "RH_WHITE": 616.0, "H_BLACK": 369, "UH_BLACK": 329, "RH_BLACK": 40.0, "H_AMIN": 53, "UH_AMIN": 30, "RH_AMIN": 23.0, "H_ASIAN": 9, "UH_ASIAN": 4, "RH_ASIAN": 5.0, "H_NHPI": 0, "UH_NHPI": 0, "RH_NHPI": 0.0, "H_OTHER": 1698, "UH_OTHER": 1327, "RH_OTHER": 371.0, "H_2MORE": 357, "UH_2MORE": 265, "RH_2MORE": 92.0, "VAP": 50573, "UVAP": 27438, "RVAP": 23135.0, "HVAP": 2769, "UHVAP": 2046, "RHVAP": 723.0, "WVAP": 40243, "UWVAP": 19844, "RWVAP": 20399.0, "BVAP": 6437, "UBVAP": 4883, "RBVAP": 1554.0, "AMINVAP": 143, "UAMINVAP": 67, "RAMINVAP": 76.0, "ASIANVAP": 424, "UASIANVAP": 272, "RASIANVAP": 152.0, "NHPIVAP": 8, "UNHPIVAP": 4, "RNHPIVAP": 4.0, "OTHERVAP": 26, "UOTHERVAP": 15, "ROTHERVAP": 11.0, "2MOREVAP": 523, "U2MOREVAP": 307, "R2MOREVAP": 216.0, "id": 5}, {"boundary_node": true, "boundary_perim": 0.40958578700704784, "area": 0.1833358694295007, "STATEFP10": "34", "COUNTYFP10": "011", "COUNTYNS10": "00882275", "GEOID10": "34011", "NAME10": "Cumberland", "NAMELSAD10": "Cumberland County", "LSAD10": "06", "CLASSFP10": "H1", "MTFCC10": "G4020", "CSAFP10": "428", "CBSAFP10": "47220", "METDIVFP10": "0", "FUNCSTAT10": "A", "ALAND10": 1252784157, "AWATER10": 502245900, "INTPTLAT10": "+39.3283873", "INTPTLON10": "-075.1216435", "POP10": 156898, "UPOP": 120769, "RPOP": 36129.0, "C_X": -75.12934220625029, "C_Y": 39.32806923397703, "TOTPOP": 156898, "UTOTPOP": 120769, "RTOTPOP": 36129.0, "NH_WHITE": 78931, "UNH_WHITE": 53892, "RNH_WHITE": 25039.0, "NH_BLACK": 29376, "UNH_BLACK": 23335, "RNH_BLACK": 6041.0, "NH_AMIN": 1102, "UNH_AMIN": 669, "RNH_AMIN": 433.0, "NH_ASIAN": 1854, "UNH_ASIAN": 1590, "RNH_ASIAN": 264.0, "NH_NHPI": 31, "UNH_NHPI": 28, "RNH_NHPI": 3.0, "NH_OTHER": 216, "UNH_OTHER": 164, "RNH_OTHER": 52.0, "NH_2MORE": 2931, "UNH_2MORE": 2271, "RNH_2MORE": 660.0, "HISP": 42457, "UHISP": 38820, "RHISP": 3637.0, "H_WHITE": 19499, "UH_WHITE": 17806, "RH_WHITE": 1693.0, "H_BLACK": 2365, "UH_BLACK": 2052, "RH_BLACK": 313.0, "H_AMIN": 644, "UH_AMIN": 528, "RH_AMIN": 116.0, "H_ASIAN": 53, "UH_ASIAN": 47, "RH_ASIAN": 6.0, "H_NHPI": 28, "UH_NHPI": 28, "RH_NHPI": 0.0, "H_OTHER": 17276, "UH_OTHER": 16057, "RH_OTHER": 1219.0, "H_2MORE": 2592, "UH_2MORE": 2302, "RH_2MORE": 290.0, "VAP": 119193, "UVAP": 89710, "RVAP": 29483.0, "HVAP": 27831, "UHVAP": 25200, "RHVAP": 2631.0, "WVAP": 65143, "UWVAP": 44701, "RWVAP": 20442.0, "BVAP": 22215, "UBVAP": 16826, "RBVAP": 5389.0, "AMINVAP": 895, "UAMINVAP": 521, "RAMINVAP": 374.0, "ASIANVAP": 1415, "UASIANVAP": 1199, "RASIANVAP": 216.0, "NHPIVAP": 19, "UNHPIVAP": 16, "RNHPIVAP": 3.0, "OTHERVAP": 142, "UOTHERVAP": 102, "ROTHERVAP": 40.0, "2MOREVAP": 1533, "U2MOREVAP": 1145, "R2MOREVAP": 388.0, "id": 6}, {"boundary_node": true, "boundary_perim": 0.31168183268478855, "area": 0.06277984360050028, "STATEFP10": "34", "COUNTYFP10": "021", "COUNTYNS10": "00882229", "GEOID10": "34021", "NAME10": "Mercer", "NAMELSAD10": "Mercer County", "LSAD10": "06", "CLASSFP10": "H1", "MTFCC10": "G4020", "CSAFP10": "408", "CBSAFP10": "45940", "METDIVFP10": "0", "FUNCSTAT10": "A", "ALAND10": 581601212, "AWATER10": 11217700, "INTPTLAT10": "+40.2825026", "INTPTLON10": "-074.7037240", "POP10": 366513, "UPOP": 353749, "RPOP": 12764.0, "C_X": -74.70168914158378, "C_Y": 40.28340475119959, "TOTPOP": 366513, "UTOTPOP": 353749, "RTOTPOP": 12764.0, "NH_WHITE": 199909, "UNH_WHITE": 188715, "RNH_WHITE": 11194.0, "NH_BLACK": 71378, "UNH_BLACK": 71053, "RNH_BLACK": 325.0, "NH_AMIN": 535, "UNH_AMIN": 526, "RNH_AMIN": 9.0, "NH_ASIAN": 32545, "UNH_ASIAN": 31888, "RNH_ASIAN": 657.0, "NH_NHPI": 146, "UNH_NHPI": 145, "RNH_NHPI": 1.0, "NH_OTHER": 630, "UNH_OTHER": 604, "RNH_OTHER": 26.0, "NH_2MORE": 6052, "UNH_2MORE": 5903, "RNH_2MORE": 149.0, "HISP": 55318, "UHISP": 54915, "RHISP": 403.0, "H_WHITE": 25102, "UH_WHITE": 24809, "RH_WHITE": 293.0, "H_BLACK": 2940, "UH_BLACK": 2932, "RH_BLACK": 8.0, "H_AMIN": 659, "UH_AMIN": 653, "RH_AMIN": 6.0, "H_ASIAN": 207, "UH_ASIAN": 202, "RH_ASIAN": 5.0, "H_NHPI": 149, "UH_NHPI": 149, "RH_NHPI": 0.0, "H_OTHER": 22226, "UH_OTHER": 22159, "RH_OTHER": 67.0, "H_2MORE": 4035, "UH_2MORE": 4011, "RH_2MORE": 24.0, "VAP": 283531, "UVAP": 273933, "RVAP": 9598.0, "HVAP": 38813, "UHVAP": 38545, "RHVAP": 268.0, "WVAP": 163810, "UWVAP": 155269, "RWVAP": 8541.0, "BVAP": 52811, "UBVAP": 52572, "RBVAP": 239.0, "AMINVAP": 389, "UAMINVAP": 382, "RAMINVAP": 7.0, "ASIANVAP": 23858, "UASIANVAP": 23391, "RASIANVAP": 467.0, "NHPIVAP": 122, "UNHPIVAP": 121, "RNHPIVAP": 1.0, "OTHERVAP": 362, "UOTHERVAP": 352, "ROTHERVAP": 10.0, "2MOREVAP": 3366, "U2MOREVAP": 3301, "R2MOREVAP": 65.0, "id": 7}, {"boundary_node": true, "boundary_perim": 1.1061039423293786, "area": 0.1672871806705001, "STATEFP10": "34", "COUNTYFP10": "009", "COUNTYNS10": "00882274", "GEOID10": "34009", "NAME10": "Cape May", "NAMELSAD10": "Cape May County", "LSAD10": "06", "CLASSFP10": "H1", "MTFCC10": "G4020", "CSAFP10": "0", "CBSAFP10": "36140", "METDIVFP10": "0", "FUNCSTAT10": "A", "ALAND10": 651187425, "AWATER10": 955684066, "INTPTLAT10": "+39.0861424", "INTPTLON10": "-074.8477157", "POP10": 97265, "UPOP": 80288, "RPOP": 16977.0, "C_X": -74.84998198765454, "C_Y": 39.08512705363587, "TOTPOP": 97265, "UTOTPOP": 80288, "RTOTPOP": 16977.0, "NH_WHITE": 84522, "UNH_WHITE": 69410, "RNH_WHITE": 15112.0, "NH_BLACK": 4244, "UNH_BLACK": 3457, "RNH_BLACK": 787.0, "NH_AMIN": 143, "UNH_AMIN": 120, "RNH_AMIN": 23.0, "NH_ASIAN": 818, "UNH_ASIAN": 662, "RNH_ASIAN": 156.0, "NH_NHPI": 32, "UNH_NHPI": 30, "RNH_NHPI": 2.0, "NH_OTHER": 85, "UNH_OTHER": 71, "RNH_OTHER": 14.0, "NH_2MORE": 1367, "UNH_2MORE": 1097, "RNH_2MORE": 270.0, "HISP": 6054, "UHISP": 5441, "RHISP": 613.0, "H_WHITE": 2847, "UH_WHITE": 2545, "RH_WHITE": 302.0, "H_BLACK": 321, "UH_BLACK": 288, "RH_BLACK": 33.0, "H_AMIN": 62, "UH_AMIN": 57, "RH_AMIN": 5.0, "H_ASIAN": 16, "UH_ASIAN": 16, "RH_ASIAN": 0.0, "H_NHPI": 4, "UH_NHPI": 2, "RH_NHPI": 2.0, "H_OTHER": 2314, "UH_OTHER": 2101, "RH_OTHER": 213.0, "H_2MORE": 490, "UH_2MORE": 432, "RH_2MORE": 58.0, "VAP": 78916, "UVAP": 65757, "RVAP": 13159.0, "HVAP": 3961, "UHVAP": 3576, "RHVAP": 385.0, "WVAP": 70269, "UWVAP": 58357, "RWVAP": 11912.0, "BVAP": 3279, "UBVAP": 2683, "RBVAP": 596.0, "AMINVAP": 115, "UAMINVAP": 96, "RAMINVAP": 19.0, "ASIANVAP": 619, "UASIANVAP": 503, "RASIANVAP": 116.0, "NHPIVAP": 26, "UNHPIVAP": 24, "RNHPIVAP": 2.0, "OTHERVAP": 41, "UOTHERVAP": 33, "ROTHERVAP": 8.0, "2MOREVAP": 606, "U2MOREVAP": 485, "R2MOREVAP": 121.0, "id": 8}, {"boundary_node": true, "boundary_perim": 0.7635834361810019, "area": 0.1824956132259982, "STATEFP10": "34", "COUNTYFP10": "025", "COUNTYNS10": "00882910", "GEOID10": "34025", "NAME10": "Monmouth", "NAMELSAD10": "Monmouth County", "LSAD10": "06", "CLASSFP10": "H1", "MTFCC10": "G4020", "CSAFP10": "408", "CBSAFP10": "35620", "METDIVFP10": "20764", "FUNCSTAT10": "A", "ALAND10": 1214167244, "AWATER10": 509002211, "INTPTLAT10": "+40.2870559", "INTPTLON10": "-074.1524457", "POP10": 630380, "UPOP": 606870, "RPOP": 23510.0, "C_X": -74.15814661718323, "C_Y": 40.28755158953225, "TOTPOP": 630380, "UTOTPOP": 606870, "RTOTPOP": 23510.0, "NH_WHITE": 483435, "UNH_WHITE": 463178, "RNH_WHITE": 20257.0, "NH_BLACK": 43931, "UNH_BLACK": 43245, "RNH_BLACK": 686.0, "NH_AMIN": 616, "UNH_AMIN": 593, "RNH_AMIN": 23.0, "NH_ASIAN": 31018, "UNH_ASIAN": 30111, "RNH_ASIAN": 907.0, "NH_NHPI": 172, "UNH_NHPI": 171, "RNH_NHPI": 1.0, "NH_OTHER": 1730, "UNH_OTHER": 1683, "RNH_OTHER": 47.0, "NH_2MORE": 8539, "UNH_2MORE": 8279, "RNH_2MORE": 260.0, "HISP": 60939, "UHISP": 59610, "RHISP": 1329.0, "H_WHITE": 37281, "UH_WHITE": 36291, "RH_WHITE": 990.0, "H_BLACK": 2512, "UH_BLACK": 2478, "RH_BLACK": 34.0, "H_AMIN": 595, "UH_AMIN": 581, "RH_AMIN": 14.0, "H_ASIAN": 240, "UH_ASIAN": 236, "RH_ASIAN": 4.0, "H_NHPI": 39, "UH_NHPI": 39, "RH_NHPI": 0.0, "H_OTHER": 16457, "UH_OTHER": 16248, "RH_OTHER": 209.0, "H_2MORE": 3815, "UH_2MORE": 3737, "RH_2MORE": 78.0, "VAP": 480081, "UVAP": 462723, "RVAP": 17358.0, "HVAP": 41337, "UHVAP": 40482, "RHVAP": 855.0, "WVAP": 376821, "UWVAP": 361704, "RWVAP": 15117.0, "BVAP": 32587, "UBVAP": 32067, "RBVAP": 520.0, "AMINVAP": 472, "UAMINVAP": 454, "RAMINVAP": 18.0, "ASIANVAP": 23096, "UASIANVAP": 22414, "RASIANVAP": 682.0, "NHPIVAP": 126, "UNHPIVAP": 125, "RNHPIVAP": 1.0, "OTHERVAP": 1227, "UOTHERVAP": 1204, "ROTHERVAP": 23.0, "2MOREVAP": 4415, "U2MOREVAP": 4273, "R2MOREVAP": 142.0, "id": 9}, {"boundary_node": false, "area": 0.03581941241849999, "STATEFP10": "34", "COUNTYFP10": "013", "COUNTYNS10": "00882276", "GEOID10": "34013", "NAME10": "Essex", "NAMELSAD10": "Essex County", "LSAD10": "06", "CLASSFP10": "H1", "MTFCC10": "G4020", "CSAFP10": "408", "CBSAFP10": "35620", "METDIVFP10": "35084", "FUNCSTAT10": "A", "ALAND10": 326888224, "AWATER10": 8854094, "INTPTLAT10": "+40.7872164", "INTPTLON10": "-074.2461361", "POP10": 783969, "UPOP": 783855, "RPOP": 114.0, "C_X": -74.24686517634355, "C_Y": 40.78707047058162, "TOTPOP": 783969, "UTOTPOP": 783855, "RTOTPOP": 114.0, "NH_WHITE": 260177, "UNH_WHITE": 260092, "RNH_WHITE": 85.0, "NH_BLACK": 308358, "UNH_BLACK": 308353, "RNH_BLACK": 5.0, "NH_AMIN": 1509, "UNH_AMIN": 1509, "RNH_AMIN": 0.0, "NH_ASIAN": 35292, "UNH_ASIAN": 35283, "RNH_ASIAN": 9.0, "NH_NHPI": 177, "UNH_NHPI": 177, "RNH_NHPI": 0.0, "NH_OTHER": 6121, "UNH_OTHER": 6121, "RNH_OTHER": 0.0, "NH_2MORE": 13218, "UNH_2MORE": 13218, "RNH_2MORE": 0.0, "HISP": 159117, "UHISP": 159102, "RHISP": 15.0, "H_WHITE": 73691, "UH_WHITE": 73685, "RH_WHITE": 6.0, "H_BLACK": 12121, "UH_BLACK": 12118, "RH_BLACK": 3.0, "H_AMIN": 1547, "UH_AMIN": 1547, "RH_AMIN": 0.0, "H_ASIAN": 497, "UH_ASIAN": 497, "RH_ASIAN": 0.0, "H_NHPI": 109, "UH_NHPI": 109, "RH_NHPI": 0.0, "H_OTHER": 59566, "UH_OTHER": 59562, "RH_OTHER": 4.0, "H_2MORE": 11586, "UH_2MORE": 11584, "RH_2MORE": 2.0, "VAP": 589051, "UVAP": 588959, "RVAP": 92.0, "HVAP": 113312, "UHVAP": 113299, "RHVAP": 13.0, "WVAP": 206921, "UWVAP": 206851, "RWVAP": 70.0, "BVAP": 227440, "UBVAP": 227435, "RBVAP": 5.0, "AMINVAP": 1091, "UAMINVAP": 1091, "RAMINVAP": 0.0, "ASIANVAP": 27293, "UASIANVAP": 27289, "RASIANVAP": 4.0, "NHPIVAP": 148, "UNHPIVAP": 148, "RNHPIVAP": 0.0, "OTHERVAP": 4619, "UOTHERVAP": 4619, "ROTHERVAP": 0.0, "2MOREVAP": 8227, "U2MOREVAP": 8227, "R2MOREVAP": 0.0, "id": 10}, {"boundary_node": true, "boundary_perim": 0.3956180308230306, "area": 0.22355192456149992, "STATEFP10": "34", "COUNTYFP10": "005", "COUNTYNS10": "00882272", "GEOID10": "34005", "NAME10": "Burlington", "NAMELSAD10": "Burlington County", "LSAD10": "06", "CLASSFP10": "H1", "MTFCC10": "G4020", "CSAFP10": "428", "CBSAFP10": "37980", "METDIVFP10": "15804", "FUNCSTAT10": "A", "ALAND10": 2068303255, "AWATER10": 55068519, "INTPTLAT10": "+39.8757857", "INTPTLON10": "-074.6630063", "POP10": 448734, "UPOP": 418834, "RPOP": 29900.0, "C_X": -74.6682033926612, "C_Y": 39.87769283106875, "TOTPOP": 448734, "UTOTPOP": 418834, "RTOTPOP": 29900.0, "NH_WHITE": 317021, "UNH_WHITE": 290840, "RNH_WHITE": 26181.0, "NH_BLACK": 71247, "UNH_BLACK": 69829, "RNH_BLACK": 1418.0, "NH_AMIN": 656, "UNH_AMIN": 621, "RNH_AMIN": 35.0, "NH_ASIAN": 19193, "UNH_ASIAN": 18654, "RNH_ASIAN": 539.0, "NH_NHPI": 193, "UNH_NHPI": 183, "RNH_NHPI": 10.0, "NH_OTHER": 1471, "UNH_OTHER": 1449, "RNH_OTHER": 22.0, "NH_2MORE": 10122, "UNH_2MORE": 9680, "RNH_2MORE": 442.0, "HISP": 28831, "UHISP": 27578, "RHISP": 1253.0, "H_WHITE": 14321, "UH_WHITE": 13513, "RH_WHITE": 808.0, "H_BLACK": 3258, "UH_BLACK": 3191, "RH_BLACK": 67.0, "H_AMIN": 329, "UH_AMIN": 316, "RH_AMIN": 13.0, "H_ASIAN": 202, "UH_ASIAN": 194, "RH_ASIAN": 8.0, "H_NHPI": 26, "UH_NHPI": 24, "RH_NHPI": 2.0, "H_OTHER": 7722, "UH_OTHER": 7457, "RH_OTHER": 265.0, "H_2MORE": 2973, "UH_2MORE": 2883, "RH_2MORE": 90.0, "VAP": 344491, "UVAP": 321325, "RVAP": 23166.0, "HVAP": 19525, "UHVAP": 18679, "RHVAP": 846.0, "WVAP": 250151, "UWVAP": 229586, "RWVAP": 20565.0, "BVAP": 53451, "UBVAP": 52395, "RBVAP": 1056.0, "AMINVAP": 513, "UAMINVAP": 486, "RAMINVAP": 27.0, "ASIANVAP": 14343, "UASIANVAP": 13937, "RASIANVAP": 406.0, "NHPIVAP": 149, "UNHPIVAP": 141, "RNHPIVAP": 8.0, "OTHERVAP": 1031, "UOTHERVAP": 1016, "ROTHERVAP": 15.0, "2MOREVAP": 5328, "U2MOREVAP": 5085, "R2MOREVAP": 243.0, "id": 11}, {"boundary_node": true, "boundary_perim": 0.1570228610774016, "area": 0.06191170481900014, "STATEFP10": "34", "COUNTYFP10": "007", "COUNTYNS10": "00882273", "GEOID10": "34007", "NAME10": "Camden", "NAMELSAD10": "Camden County", "LSAD10": "06", "CLASSFP10": "H1", "MTFCC10": "G4020", "CSAFP10": "428", "CBSAFP10": "37980", "METDIVFP10": "15804", "FUNCSTAT10": "A", "ALAND10": 573067842, "AWATER10": 15616906, "INTPTLAT10": "+39.8023520", "INTPTLON10": "-074.9612507", "POP10": 513657, "UPOP": 505349, "RPOP": 8308.0, "C_X": -74.95975634048445, "C_Y": 39.80353215554339, "TOTPOP": 513657, "UTOTPOP": 505349, "RTOTPOP": 8308.0, "NH_WHITE": 309648, "UNH_WHITE": 303594, "RNH_WHITE": 6054.0, "NH_BLACK": 94762, "UNH_BLACK": 93638, "RNH_BLACK": 1124.0, "NH_AMIN": 859, "UNH_AMIN": 839, "RNH_AMIN": 20.0, "NH_ASIAN": 26043, "UNH_ASIAN": 25858, "RNH_ASIAN": 185.0, "NH_NHPI": 106, "UNH_NHPI": 105, "RNH_NHPI": 1.0, "NH_OTHER": 731, "UNH_OTHER": 728, "RNH_OTHER": 3.0, "NH_2MORE": 8384, "UNH_2MORE": 8275, "RNH_2MORE": 109.0, "HISP": 73124, "UHISP": 72312, "RHISP": 812.0, "H_WHITE": 25741, "UH_WHITE": 25437, "RH_WHITE": 304.0, "H_BLACK": 5679, "UH_BLACK": 5614, "RH_BLACK": 65.0, "H_AMIN": 749, "UH_AMIN": 740, "RH_AMIN": 9.0, "H_ASIAN": 214, "UH_ASIAN": 214, "RH_ASIAN": 0.0, "H_NHPI": 59, "UH_NHPI": 59, "RH_NHPI": 0.0, "H_OTHER": 35623, "UH_OTHER": 35231, "RH_OTHER": 392.0, "H_2MORE": 5059, "UH_2MORE": 5017, "RH_2MORE": 42.0, "VAP": 388540, "UVAP": 382002, "RVAP": 6538.0, "HVAP": 47518, "UHVAP": 46967, "RHVAP": 551.0, "WVAP": 248010, "UWVAP": 243051, "RWVAP": 4959.0, "BVAP": 68018, "UBVAP": 67200, "RBVAP": 818.0, "AMINVAP": 639, "UAMINVAP": 622, "RAMINVAP": 17.0, "ASIANVAP": 19581, "UASIANVAP": 19450, "RASIANVAP": 131.0, "NHPIVAP": 83, "UNHPIVAP": 82, "RNHPIVAP": 1.0, "OTHERVAP": 441, "UOTHERVAP": 441, "ROTHERVAP": 0.0, "2MOREVAP": 4250, "U2MOREVAP": 4189, "R2MOREVAP": 61.0, "id": 12}, {"boundary_node": true, "boundary_perim": 0.4536796951359896, "area": 0.12048050176699998, "STATEFP10": "34", "COUNTYFP10": "019", "COUNTYNS10": "00882228", "GEOID10": "34019", "NAME10": "Hunterdon", "NAMELSAD10": "Hunterdon County", "LSAD10": "06", "CLASSFP10": "H1", "MTFCC10": "G4020", "CSAFP10": "408", "CBSAFP10": "35620", "METDIVFP10": "35084", "FUNCSTAT10": "A", "ALAND10": 1108046234, "AWATER10": 24910908, "INTPTLAT10": "+40.5652832", "INTPTLON10": "-074.9119694", "POP10": 128349, "UPOP": 64727, "RPOP": 63622.0, "C_X": -74.9122234604504, "C_Y": 40.56728226407335, "TOTPOP": 128349, "UTOTPOP": 64727, "RTOTPOP": 63622.0, "NH_WHITE": 112607, "UNH_WHITE": 54528, "RNH_WHITE": 58079.0, "NH_BLACK": 3233, "UNH_BLACK": 2037, "RNH_BLACK": 1196.0, "NH_AMIN": 97, "UNH_AMIN": 49, "RNH_AMIN": 48.0, "NH_ASIAN": 4155, "UNH_ASIAN": 2899, "RNH_ASIAN": 1256.0, "NH_NHPI": 27, "UNH_NHPI": 13, "RNH_NHPI": 14.0, "NH_OTHER": 166, "UNH_OTHER": 82, "RNH_OTHER": 84.0, "NH_2MORE": 1342, "UNH_2MORE": 753, "RNH_2MORE": 589.0, "HISP": 6722, "UHISP": 4366, "RHISP": 2356.0, "H_WHITE": 4657, "UH_WHITE": 2981, "RH_WHITE": 1676.0, "H_BLACK": 218, "UH_BLACK": 111, "RH_BLACK": 107.0, "H_AMIN": 70, "UH_AMIN": 55, "RH_AMIN": 15.0, "H_ASIAN": 26, "UH_ASIAN": 20, "RH_ASIAN": 6.0, "H_NHPI": 10, "UH_NHPI": 9, "RH_NHPI": 1.0, "H_OTHER": 1404, "UH_OTHER": 965, "RH_OTHER": 439.0, "H_2MORE": 337, "UH_2MORE": 225, "RH_2MORE": 112.0, "VAP": 98132, "UVAP": 49872, "RVAP": 48260.0, "HVAP": 4771, "UHVAP": 3142, "RHVAP": 1629.0, "WVAP": 86790, "UWVAP": 42418, "RWVAP": 44372.0, "BVAP": 2717, "UBVAP": 1722, "RBVAP": 995.0, "AMINVAP": 69, "UAMINVAP": 37, "RAMINVAP": 32.0, "ASIANVAP": 3039, "UASIANVAP": 2141, "RASIANVAP": 898.0, "NHPIVAP": 20, "UNHPIVAP": 11, "RNHPIVAP": 9.0, "OTHERVAP": 102, "UOTHERVAP": 49, "ROTHERVAP": 53.0, "2MOREVAP": 624, "U2MOREVAP": 352, "R2MOREVAP": 272.0, "id": 13}, {"boundary_node": false, "area": 0.1332302030234999, "STATEFP10": "34", "COUNTYFP10": "027", "COUNTYNS10": "00882231", "GEOID10": "34027", "NAME10": "Morris", "NAMELSAD10": "Morris County", "LSAD10": "06", "CLASSFP10": "H1", "MTFCC10": "G4020", "CSAFP10": "408", "CBSAFP10": "35620", "METDIVFP10": "35084", "FUNCSTAT10": "A", "ALAND10": 1191852367, "AWATER10": 55550237, "INTPTLAT10": "+40.8585805", "INTPTLON10": "-074.5474268", "POP10": 492276, "UPOP": 458952, "RPOP": 33324.0, "C_X": -74.5444628333458, "C_Y": 40.86203372739054, "TOTPOP": 492276, "UTOTPOP": 458952, "RTOTPOP": 33324.0, "NH_WHITE": 369551, "UNH_WHITE": 339984, "RNH_WHITE": 29567.0, "NH_BLACK": 14134, "UNH_BLACK": 13686, "RNH_BLACK": 448.0, "NH_AMIN": 369, "UNH_AMIN": 336, "RNH_AMIN": 33.0, "NH_ASIAN": 43862, "UNH_ASIAN": 42564, "RNH_ASIAN": 1298.0, "NH_NHPI": 70, "UNH_NHPI": 62, "RNH_NHPI": 8.0, "NH_OTHER": 806, "UNH_OTHER": 744, "RNH_OTHER": 62.0, "NH_2MORE": 7002, "UNH_2MORE": 6607, "RNH_2MORE": 395.0, "HISP": 56482, "UHISP": 54969, "RHISP": 1513.0, "H_WHITE": 37132, "UH_WHITE": 35947, "RH_WHITE": 1185.0, "H_BLACK": 1226, "UH_BLACK": 1189, "RH_BLACK": 37.0, "H_AMIN": 436, "UH_AMIN": 427, "RH_AMIN": 9.0, "H_ASIAN": 207, "UH_ASIAN": 200, "RH_ASIAN": 7.0, "H_NHPI": 36, "UH_NHPI": 36, "RH_NHPI": 0.0, "H_OTHER": 14104, "UH_OTHER": 13905, "RH_OTHER": 199.0, "H_2MORE": 3341, "UH_2MORE": 3265, "RH_2MORE": 76.0, "VAP": 374581, "UVAP": 350352, "RVAP": 24229.0, "HVAP": 40669, "UHVAP": 39684, "RHVAP": 985.0, "WVAP": 286126, "UWVAP": 264332, "RWVAP": 21794.0, "BVAP": 10854, "UBVAP": 10559, "RBVAP": 295.0, "AMINVAP": 268, "UAMINVAP": 240, "RAMINVAP": 28.0, "ASIANVAP": 32741, "UASIANVAP": 31824, "RASIANVAP": 917.0, "NHPIVAP": 59, "UNHPIVAP": 53, "RNHPIVAP": 6.0, "OTHERVAP": 478, "UOTHERVAP": 436, "ROTHERVAP": 42.0, "2MOREVAP": 3386, "U2MOREVAP": 3224, "R2MOREVAP": 162.0, "id": 14}, {"boundary_node": true, "boundary_perim": 0.8462939165358598, "area": 0.14881633422099938, "STATEFP10": "34", "COUNTYFP10": "037", "COUNTYNS10": "00882236", "GEOID10": "34037", "NAME10": "Sussex", "NAMELSAD10": "Sussex County", "LSAD10": "06", "CLASSFP10": "H1", "MTFCC10": "G4020", "CSAFP10": "408", "CBSAFP10": "35620", "METDIVFP10": "35084", "FUNCSTAT10": "A", "ALAND10": 1344239274, "AWATER10": 43327484, "INTPTLAT10": "+41.1374239", "INTPTLON10": "-074.6918545", "POP10": 149265, "UPOP": 89783, "RPOP": 59482.0, "C_X": -74.69024110915566, "C_Y": 41.13949524324351, "TOTPOP": 149265, "UTOTPOP": 89783, "RTOTPOP": 59482.0, "NH_WHITE": 132484, "UNH_WHITE": 78004, "RNH_WHITE": 54480.0, "NH_BLACK": 2448, "UNH_BLACK": 1765, "RNH_BLACK": 683.0, "NH_AMIN": 147, "UNH_AMIN": 104, "RNH_AMIN": 43.0, "NH_ASIAN": 2605, "UNH_ASIAN": 1780, "RNH_ASIAN": 825.0, "NH_NHPI": 29, "UNH_NHPI": 26, "RNH_NHPI": 3.0, "NH_OTHER": 164, "UNH_OTHER": 100, "RNH_OTHER": 64.0, "NH_2MORE": 1771, "UNH_2MORE": 1089, "RNH_2MORE": 682.0, "HISP": 9617, "UHISP": 6915, "RHISP": 2702.0, "H_WHITE": 7020, "UH_WHITE": 5016, "RH_WHITE": 2004.0, "H_BLACK": 229, "UH_BLACK": 156, "RH_BLACK": 73.0, "H_AMIN": 87, "UH_AMIN": 55, "RH_AMIN": 32.0, "H_ASIAN": 37, "UH_ASIAN": 22, "RH_ASIAN": 15.0, "H_NHPI": 7, "UH_NHPI": 7, "RH_NHPI": 0.0, "H_OTHER": 1619, "UH_OTHER": 1206, "RH_OTHER": 413.0, "H_2MORE": 618, "UH_2MORE": 453, "RH_2MORE": 165.0, "VAP": 113492, "UVAP": 68504, "RVAP": 44988.0, "HVAP": 6343, "UHVAP": 4570, "RHVAP": 1773.0, "WVAP": 102360, "UWVAP": 60611, "RWVAP": 41749.0, "BVAP": 1751, "UBVAP": 1282, "RBVAP": 469.0, "AMINVAP": 118, "UAMINVAP": 83, "RAMINVAP": 35.0, "ASIANVAP": 1971, "UASIANVAP": 1369, "RASIANVAP": 602.0, "NHPIVAP": 22, "UNHPIVAP": 19, "RNHPIVAP": 3.0, "OTHERVAP": 101, "UOTHERVAP": 61, "ROTHERVAP": 40.0, "2MOREVAP": 826, "U2MOREVAP": 509, "R2MOREVAP": 317.0, "id": 15}, {"boundary_node": false, "area": 0.08396012726050013, "STATEFP10": "34", "COUNTYFP10": "035", "COUNTYNS10": "00882234", "GEOID10": "34035", "NAME10": "Somerset", "NAMELSAD10": "Somerset County", "LSAD10": "06", "CLASSFP10": "H1", "MTFCC10": "G4020", "CSAFP10": "408", "CBSAFP10": "35620", "METDIVFP10": "20764", "FUNCSTAT10": "A", "ALAND10": 781692692, "AWATER10": 7883404, "INTPTLAT10": "+40.5655217", "INTPTLON10": "-074.6199299", "POP10": 323444, "UPOP": 304708, "RPOP": 18736.0, "C_X": -74.61631321049607, "C_Y": 40.5635245145533, "TOTPOP": 323444, "UTOTPOP": 304708, "RTOTPOP": 18736.0, "NH_WHITE": 201849, "UNH_WHITE": 186233, "RNH_WHITE": 15616.0, "NH_BLACK": 27480, "UNH_BLACK": 26950, "RNH_BLACK": 530.0, "NH_AMIN": 285, "UNH_AMIN": 268, "RNH_AMIN": 17.0, "NH_ASIAN": 45473, "UNH_ASIAN": 44057, "RNH_ASIAN": 1416.0, "NH_NHPI": 72, "UNH_NHPI": 71, "RNH_NHPI": 1.0, "NH_OTHER": 786, "UNH_OTHER": 751, "RNH_OTHER": 35.0, "NH_2MORE": 5408, "UNH_2MORE": 5144, "RNH_2MORE": 264.0, "HISP": 42091, "UHISP": 41234, "RHISP": 857.0, "H_WHITE": 24759, "UH_WHITE": 24171, "RH_WHITE": 588.0, "H_BLACK": 1463, "UH_BLACK": 1438, "RH_BLACK": 25.0, "H_AMIN": 271, "UH_AMIN": 265, "RH_AMIN": 6.0, "H_ASIAN": 177, "UH_ASIAN": 174, "RH_ASIAN": 3.0, "H_NHPI": 22, "UH_NHPI": 22, "RH_NHPI": 0.0, "H_OTHER": 12574, "UH_OTHER": 12384, "RH_OTHER": 190.0, "H_2MORE": 2825, "UH_2MORE": 2780, "RH_2MORE": 45.0, "VAP": 242609, "UVAP": 228690, "RVAP": 13919.0, "HVAP": 29131, "UHVAP": 28578, "RHVAP": 553.0, "WVAP": 157519, "UWVAP": 145671, "RWVAP": 11848.0, "BVAP": 20037, "UBVAP": 19673, "RBVAP": 364.0, "AMINVAP": 179, "UAMINVAP": 167, "RAMINVAP": 12.0, "ASIANVAP": 32701, "UASIANVAP": 31687, "RASIANVAP": 1014.0, "NHPIVAP": 54, "UNHPIVAP": 53, "RNHPIVAP": 1.0, "OTHERVAP": 456, "UOTHERVAP": 438, "ROTHERVAP": 18.0, "2MOREVAP": 2532, "U2MOREVAP": 2423, "R2MOREVAP": 109.0, "id": 16}, {"boundary_node": true, "boundary_perim": 0.694457801733235, "area": 0.24956898690849996, "STATEFP10": "34", "COUNTYFP10": "029", "COUNTYNS10": "00882279", "GEOID10": "34029", "NAME10": "Ocean", "NAMELSAD10": "Ocean County", "LSAD10": "06", "CLASSFP10": "H1", "MTFCC10": "G4020", "CSAFP10": "408", "CBSAFP10": "35620", "METDIVFP10": "20764", "FUNCSTAT10": "A", "ALAND10": 1628534966, "AWATER10": 742342470, "INTPTLAT10": "+39.8658497", "INTPTLON10": "-074.2630271", "POP10": 576567, "UPOP": 559856, "RPOP": 16711.0, "C_X": -74.25002561990577, "C_Y": 39.866000170719765, "TOTPOP": 576567, "UTOTPOP": 559856, "RTOTPOP": 16711.0, "NH_WHITE": 495534, "UNH_WHITE": 480685, "RNH_WHITE": 14849.0, "NH_BLACK": 16583, "UNH_BLACK": 16148, "RNH_BLACK": 435.0, "NH_AMIN": 454, "UNH_AMIN": 427, "RNH_AMIN": 27.0, "NH_ASIAN": 9924, "UNH_ASIAN": 9665, "RNH_ASIAN": 259.0, "NH_NHPI": 92, "UNH_NHPI": 88, "RNH_NHPI": 4.0, "NH_OTHER": 558, "UNH_OTHER": 543, "RNH_OTHER": 15.0, "NH_2MORE": 5639, "UNH_2MORE": 5401, "RNH_2MORE": 238.0, "HISP": 47783, "UHISP": 46899, "RHISP": 884.0, "H_WHITE": 29043, "UH_WHITE": 28460, "RH_WHITE": 583.0, "H_BLACK": 1581, "UH_BLACK": 1554, "RH_BLACK": 27.0, "H_AMIN": 512, "UH_AMIN": 509, "RH_AMIN": 3.0, "H_ASIAN": 157, "UH_ASIAN": 157, "RH_ASIAN": 0.0, "H_NHPI": 37, "UH_NHPI": 34, "RH_NHPI": 3.0, "H_OTHER": 13607, "UH_OTHER": 13421, "RH_OTHER": 186.0, "H_2MORE": 2846, "UH_2MORE": 2764, "RH_2MORE": 82.0, "VAP": 441648, "UVAP": 428665, "RVAP": 12983.0, "HVAP": 31236, "UHVAP": 30685, "RHVAP": 551.0, "WVAP": 387283, "UWVAP": 375495, "RWVAP": 11788.0, "BVAP": 11907, "UBVAP": 11610, "RBVAP": 297.0, "AMINVAP": 369, "UAMINVAP": 347, "RAMINVAP": 22.0, "ASIANVAP": 7564, "UASIANVAP": 7373, "RASIANVAP": 191.0, "NHPIVAP": 72, "UNHPIVAP": 69, "RNHPIVAP": 3.0, "OTHERVAP": 329, "UOTHERVAP": 318, "ROTHERVAP": 11.0, "2MOREVAP": 2888, "U2MOREVAP": 2768, "R2MOREVAP": 120.0, "id": 17}, {"boundary_node": true, "boundary_perim": 0.1674972826011707, "area": 0.05466424290549982, "STATEFP10": "34", "COUNTYFP10": "031", "COUNTYNS10": "00882232", "GEOID10": "34031", "NAME10": "Passaic", "NAMELSAD10": "Passaic County", "LSAD10": "06", "CLASSFP10": "H1", "MTFCC10": "G4020", "CSAFP10": "408", "CBSAFP10": "35620", "METDIVFP10": "35644", "FUNCSTAT10": "A", "ALAND10": 478093122, "AWATER10": 32407089, "INTPTLAT10": "+41.0337634", "INTPTLON10": "-074.3003074", "POP10": 501226, "UPOP": 489146, "RPOP": 12080.0, "C_X": -74.30037292291172, "C_Y": 41.03369716635053, "TOTPOP": 501226, "UTOTPOP": 489146, "RTOTPOP": 12080.0, "NH_WHITE": 227144, "UNH_WHITE": 216495, "RNH_WHITE": 10649.0, "NH_BLACK": 55480, "UNH_BLACK": 55294, "RNH_BLACK": 186.0, "NH_AMIN": 769, "UNH_AMIN": 602, "RNH_AMIN": 167.0, "NH_ASIAN": 24556, "UNH_ASIAN": 24394, "RNH_ASIAN": 162.0, "NH_NHPI": 53, "UNH_NHPI": 53, "RNH_NHPI": 0.0, "NH_OTHER": 1368, "UNH_OTHER": 1334, "RNH_OTHER": 34.0, "NH_2MORE": 6179, "UNH_2MORE": 5953, "RNH_2MORE": 226.0, "HISP": 185677, "UHISP": 185021, "RHISP": 656.0, "H_WHITE": 86857, "UH_WHITE": 86406, "RH_WHITE": 451.0, "H_BLACK": 8815, "UH_BLACK": 8799, "RH_BLACK": 16.0, "H_AMIN": 2579, "UH_AMIN": 2549, "RH_AMIN": 30.0, "H_ASIAN": 536, "UH_ASIAN": 534, "RH_ASIAN": 2.0, "H_NHPI": 103, "UH_NHPI": 103, "RH_NHPI": 0.0, "H_OTHER": 74367, "UH_OTHER": 74255, "RH_OTHER": 112.0, "H_2MORE": 12420, "UH_2MORE": 12375, "RH_2MORE": 45.0, "VAP": 376613, "UVAP": 367255, "RVAP": 9358.0, "HVAP": 128930, "UHVAP": 128494, "RHVAP": 436.0, "WVAP": 182502, "UWVAP": 174121, "RWVAP": 8381.0, "BVAP": 41212, "UBVAP": 41069, "RBVAP": 143.0, "AMINVAP": 549, "UAMINVAP": 423, "RAMINVAP": 126.0, "ASIANVAP": 18645, "UASIANVAP": 18522, "RASIANVAP": 123.0, "NHPIVAP": 44, "UNHPIVAP": 44, "RNHPIVAP": 0.0, "OTHERVAP": 828, "UOTHERVAP": 809, "ROTHERVAP": 19.0, "2MOREVAP": 3903, "U2MOREVAP": 3773, "R2MOREVAP": 130.0, "id": 18}, {"boundary_node": true, "boundary_perim": 0.08890493757863549, "area": 0.029069571095999957, "STATEFP10": "34", "COUNTYFP10": "039", "COUNTYNS10": "00882235", "GEOID10": "34039", "NAME10": "Union", "NAMELSAD10": "Union County", "LSAD10": "06", "CLASSFP10": "H1", "MTFCC10": "G4020", "CSAFP10": "408", "CBSAFP10": "35620", "METDIVFP10": "35084", "FUNCSTAT10": "A", "ALAND10": 266393116, "AWATER10": 6595128, "INTPTLAT10": "+40.6598707", "INTPTLON10": "-074.3086957", "POP10": 536499, "UPOP": 536499, "RPOP": 0.0, "C_X": -74.30858876038268, "C_Y": 40.659796882812316, "TOTPOP": 536499, "UTOTPOP": 536499, "RTOTPOP": 0.0, "NH_WHITE": 243312, "UNH_WHITE": 243312, "RNH_WHITE": 0.0, "NH_BLACK": 111705, "UNH_BLACK": 111705, "RNH_BLACK": 0.0, "NH_AMIN": 546, "UNH_AMIN": 546, "RNH_AMIN": 0.0, "NH_ASIAN": 24496, "UNH_ASIAN": 24496, "RNH_ASIAN": 0.0, "NH_NHPI": 107, "UNH_NHPI": 107, "RNH_NHPI": 0.0, "NH_OTHER": 2279, "UNH_OTHER": 2279, "RNH_OTHER": 0.0, "NH_2MORE": 7350, "UNH_2MORE": 7350, "RNH_2MORE": 0.0, "HISP": 146704, "UHISP": 146704, "RHISP": 0.0, "H_WHITE": 85740, "UH_WHITE": 85740, "RH_WHITE": 0.0, "H_BLACK": 6608, "UH_BLACK": 6608, "RH_BLACK": 0.0, "H_AMIN": 1534, "UH_AMIN": 1534, "RH_AMIN": 0.0, "H_ASIAN": 343, "UH_ASIAN": 343, "RH_ASIAN": 0.0, "H_NHPI": 56, "UH_NHPI": 56, "RH_NHPI": 0.0, "H_OTHER": 43217, "UH_OTHER": 43217, "RH_OTHER": 0.0, "H_2MORE": 9206, "UH_2MORE": 9206, "RH_2MORE": 0.0, "VAP": 405241, "UVAP": 405241, "RVAP": 0.0, "HVAP": 105722, "UHVAP": 105722, "RHVAP": 0.0, "WVAP": 192241, "UWVAP": 192241, "RWVAP": 0.0, "BVAP": 82444, "UBVAP": 82444, "RBVAP": 0.0, "AMINVAP": 401, "UAMINVAP": 401, "RAMINVAP": 0.0, "ASIANVAP": 18687, "UASIANVAP": 18687, "RASIANVAP": 0.0, "NHPIVAP": 94, "UNHPIVAP": 94, "RNHPIVAP": 0.0, "OTHERVAP": 1505, "UOTHERVAP": 1505, "ROTHERVAP": 0.0, "2MOREVAP": 4147, "U2MOREVAP": 4147, "R2MOREVAP": 0.0, "id": 19}, {"boundary_node": true, "boundary_perim": 0.1680827842825765, "area": 0.08874816186549979, "STATEFP10": "34", "COUNTYFP10": "023", "COUNTYNS10": "00882230", "GEOID10": "34023", "NAME10": "Middlesex", "NAMELSAD10": "Middlesex County", "LSAD10": "06", "CLASSFP10": "H1", "MTFCC10": "G4020", "CSAFP10": "408", "CBSAFP10": "35620", "METDIVFP10": "20764", "FUNCSTAT10": "A", "ALAND10": 800083087, "AWATER10": 36034482, "INTPTLAT10": "+40.4395925", "INTPTLON10": "-074.4075851", "POP10": 809858, "UPOP": 804397, "RPOP": 5461.0, "C_X": -74.4088906140079, "C_Y": 40.4400422381726, "TOTPOP": 809858, "UTOTPOP": 804397, "RTOTPOP": 5461.0, "NH_WHITE": 398724, "UNH_WHITE": 394483, "RNH_WHITE": 4241.0, "NH_BLACK": 71557, "UNH_BLACK": 71434, "RNH_BLACK": 123.0, "NH_AMIN": 1193, "UNH_AMIN": 1180, "RNH_AMIN": 13.0, "NH_ASIAN": 172534, "UNH_ASIAN": 171779, "RNH_ASIAN": 755.0, "NH_NHPI": 156, "UNH_NHPI": 156, "RNH_NHPI": 0.0, "NH_OTHER": 2720, "UNH_OTHER": 2708, "RNH_OTHER": 12.0, "NH_2MORE": 13999, "UNH_2MORE": 13918, "RNH_2MORE": 81.0, "HISP": 148975, "UHISP": 148739, "RHISP": 236.0, "H_WHITE": 75865, "UH_WHITE": 75704, "RH_WHITE": 161.0, "H_BLACK": 6905, "UH_BLACK": 6905, "RH_BLACK": 0.0, "H_AMIN": 1584, "UH_AMIN": 1584, "RH_AMIN": 0.0, "H_ASIAN": 759, "UH_ASIAN": 758, "RH_ASIAN": 1.0, "H_NHPI": 95, "UH_NHPI": 95, "RH_NHPI": 0.0, "H_OTHER": 53849, "UH_OTHER": 53784, "RH_OTHER": 65.0, "H_2MORE": 9918, "UH_2MORE": 9909, "RH_2MORE": 9.0, "VAP": 624401, "UVAP": 620187, "RVAP": 4214.0, "HVAP": 103155, "UHVAP": 102995, "RHVAP": 160.0, "WVAP": 329104, "UWVAP": 325735, "RWVAP": 3369.0, "BVAP": 53383, "UBVAP": 53286, "RBVAP": 97.0, "AMINVAP": 658, "UAMINVAP": 650, "RAMINVAP": 8.0, "ASIANVAP": 127602, "UASIANVAP": 127080, "RASIANVAP": 522.0, "NHPIVAP": 125, "UNHPIVAP": 125, "RNHPIVAP": 0.0, "OTHERVAP": 1869, "UOTHERVAP": 1861, "ROTHERVAP": 8.0, "2MOREVAP": 8505, "U2MOREVAP": 8455, "R2MOREVAP": 50.0, "id": 20}], "adjacency": [[{"shared_perim": 0.03897480993206533, "id": 19}, {"shared_perim": 0.18231605721806404, "id": 10}, {"shared_perim": 0.24930434887526562, "id": 2}], [{"shared_perim": 0.4870179078211963, "id": 8}, {"shared_perim": 0.27391071790590255, "id": 6}, {"shared_perim": 0.1428758393365428, "id": 4}, {"shared_perim": 0.18613050527038671, "id": 12}, {"shared_perim": 0.2374750289398519, "id": 17}, {"shared_perim": 0.5293494570120943, "id": 11}], [{"shared_perim": 0.24930434887526562, "id": 0}, {"shared_perim": 0.04257450254754637, "id": 10}, {"shared_perim": 0.4866374207645263, "id": 18}], [{"shared_perim": 0.40603916540173385, "id": 13}, {"shared_perim": 0.22762598558138983, "id": 14}, {"shared_perim": 0.2702301725757917, "id": 15}], [{"shared_perim": 0.1428758393365428, "id": 1}, {"shared_perim": 0.09375969799491678, "id": 6}, {"shared_perim": 0.6120653023313127, "id": 5}, {"shared_perim": 0.6151218984925804, "id": 12}], [{"shared_perim": 0.6120653023313127, "id": 4}, {"shared_perim": 0.799701499024606, "id": 6}], [{"shared_perim": 0.27391071790590255, "id": 1}, {"shared_perim": 0.09375969799491678, "id": 4}, {"shared_perim": 0.799701499024606, "id": 5}, {"shared_perim": 0.5066672348560965, "id": 8}], [{"shared_perim": 0.2599126966038256, "id": 11}, {"shared_perim": 0.2288010186496349, "id": 9}, {"shared_perim": 0.2687848887128194, "id": 20}, {"shared_perim": 0.2827054212475661, "id": 13}, {"shared_perim": 0.17070893407969617, "id": 16}], [{"shared_perim": 0.4870179078211963, "id": 1}, {"shared_perim": 0.5066672348560965, "id": 6}], [{"shared_perim": 0.2288010186496349, "id": 7}, {"shared_perim": 0.7710919229403955, "id": 17}, {"shared_perim": 0.06867526537525631, "id": 11}, {"shared_perim": 0.3896273295131866, "id": 20}], [{"shared_perim": 0.18231605721806404, "id": 0}, {"shared_perim": 0.04257450254754637, "id": 2}, {"shared_perim": 0.26702384827569625, "id": 19}, {"shared_perim": 0.43567966645925504, "id": 14}, {"shared_perim": 0.17059029669642442, "id": 18}], [{"shared_perim": 0.5293494570120943, "id": 1}, {"shared_perim": 0.2599126966038256, "id": 7}, {"shared_perim": 0.06867526537525631, "id": 9}, {"shared_perim": 0.5704800792100805, "id": 12}, {"shared_perim": 0.5885974974744999, "id": 17}], [{"shared_perim": 0.18613050527038671, "id": 1}, {"shared_perim": 0.6151218984925804, "id": 4}, {"shared_perim": 0.5704800792100805, "id": 11}], [{"shared_perim": 0.40603916540173385, "id": 3}, {"shared_perim": 0.2827054212475661, "id": 7}, {"shared_perim": 0.4485291575395435, "id": 16}, {"shared_perim": 0.18660448031122107, "id": 14}], [{"shared_perim": 0.22762598558138983, "id": 3}, {"shared_perim": 0.43567966645925504, "id": 10}, {"shared_perim": 0.18660448031122107, "id": 13}, {"shared_perim": 0.4546896350874404, "id": 16}, {"shared_perim": 0.1437881194384188, "id": 19}, {"shared_perim": 0.545531299119664, "id": 18}, {"shared_perim": 0.38799445221725753, "id": 15}], [{"shared_perim": 0.2702301725757917, "id": 3}, {"shared_perim": 0.38799445221725753, "id": 14}, {"shared_perim": 0.18020783794863798, "id": 18}], [{"shared_perim": 0.17070893407969617, "id": 7}, {"shared_perim": 0.4485291575395435, "id": 13}, {"shared_perim": 0.4546896350874404, "id": 14}, {"shared_perim": 0.4144622484888066, "id": 20}, {"shared_perim": 0.19428782492366842, "id": 19}], [{"shared_perim": 0.2374750289398519, "id": 1}, {"shared_perim": 0.7710919229403955, "id": 9}, {"shared_perim": 0.5885974974744999, "id": 11}], [{"shared_perim": 0.4866374207645263, "id": 2}, {"shared_perim": 0.17059029669642442, "id": 10}, {"shared_perim": 0.545531299119664, "id": 14}, {"shared_perim": 0.18020783794863798, "id": 15}], [{"shared_perim": 0.03897480993206533, "id": 0}, {"shared_perim": 0.26702384827569625, "id": 10}, {"shared_perim": 0.1437881194384188, "id": 14}, {"shared_perim": 0.19428782492366842, "id": 16}, {"shared_perim": 0.29192282174834827, "id": 20}], [{"shared_perim": 0.2687848887128194, "id": 7}, {"shared_perim": 0.3896273295131866, "id": 9}, {"shared_perim": 0.4144622484888066, "id": 16}, {"shared_perim": 0.29192282174834827, "id": 19}]]}